markat/__init__.py
markat/cli.py
markat-0.1.0.dist-info/METADATA
markat-0.1.0.dist-info/WHEEL
markat-0.1.0.dist-info/entry_points.txt
markat-0.1.0.dist-info/licenses/LICENSE
markat-0.1.0.dist-info/RECORD
