Metadata-Version: 2.4
Name: markat
Version: 0.1.0
Summary: Colorful CLI for slicing Markdown sections via dotted paths
Project-URL: Homepage, https://github.com/tcsenpai/markat
Project-URL: Repository, https://github.com/tcsenpai/markat
Author-email: tcsenpai <tcsenpai@discus.sh>
License: MIT License
License-File: LICENSE
Keywords: cli,documentation,markdown,utilities
Classifier: Environment :: Console
Classifier: License :: OSI Approved :: MIT License
Classifier: Programming Language :: Python
Classifier: Programming Language :: Python :: 3
Classifier: Programming Language :: Python :: 3.12
Classifier: Topic :: Text Processing
Requires-Python: >=3.12
